MANIFEST.in
README.rst
ptknows.py
setup.py
examples/conftest.py
examples/requirements.txt
examples/test_hello.py
examples/test_world.py
pytest_knows.egg-info/PKG-INFO
pytest_knows.egg-info/SOURCES.txt
pytest_knows.egg-info/dependency_links.txt
pytest_knows.egg-info/entry_points.txt
pytest_knows.egg-info/requires.txt
pytest_knows.egg-info/top_level.txt
pytest_knows.egg-info/zip-safe