Metadata-Version: 1.0
Name: pytest-knows
Version: 0.1.5
Summary: A pytest plugin that can automaticly skip test case based on dependence info calculated by trace
Home-page: https://github.com/mapix/ptknows
Author: mapix
Author-email: mapix.me@gmail.com
License: UNKNOWN
Platform: UNKNOWN
